aiida_uppasd2/UppASD_BaseWorkflow.py
aiida_uppasd2/UppASD_Calculations.py
aiida_uppasd2/UppASD_Clis.py
aiida_uppasd2/UppASD_GenericLoopWorkflow.py
aiida_uppasd2/UppASD_Parsers.py
aiida_uppasd2/__init__.py
aiida_uppasd2-2.0.1.dist-info/LICENSE
aiida_uppasd2-2.0.1.dist-info/METADATA
aiida_uppasd2-2.0.1.dist-info/WHEEL
aiida_uppasd2-2.0.1.dist-info/entry_points.txt
aiida_uppasd2-2.0.1.dist-info/top_level.txt
aiida_uppasd2-2.0.1.dist-info/RECORD
