Metadata-Version: 2.1
Name: aiida-uppasd2
Version: 2.0.1
Summary: AiiDA plugin for UppASD version 2
Author-email: Qichen Xu <mxjk851@gmail.com>
License: GNU GENERAL PUBLIC LICENSE
Project-URL: Source, https://github.com/MXJK851/aiida-uppasd2
Keywords: aiida,plugin
Classifier: Programming Language :: Python
Classifier: Intended Audience :: Science/Research
Classifier: Framework :: AiiDA
Requires-Python: >=3.7
License-File: LICENSE
Requires-Dist: aiida-core <3,>=2.0
Requires-Dist: voluptuous
Provides-Extra: pre-commit
Requires-Dist: pre-commit ~=2.2 ; extra == 'pre-commit'
Requires-Dist: pylint ~=2.15.10 ; extra == 'pre-commit'
Provides-Extra: testing
Requires-Dist: pgtest ~=1.3.1 ; extra == 'testing'
Requires-Dist: wheel ~=0.31 ; extra == 'testing'
Requires-Dist: coverage[toml] ; extra == 'testing'
Requires-Dist: pytest ~=6.0 ; extra == 'testing'
Requires-Dist: pytest-cov ; extra == 'testing'
